cplxmodule/__init__.py
cplxmodule/__version__.py
cplxmodule/cplx.py
cplxmodule/nn/__init__.py
cplxmodule/nn/init.py
cplxmodule/nn/masked/__init__.py
cplxmodule/nn/masked/base.py
cplxmodule/nn/masked/complex.py
cplxmodule/nn/masked/real.py
cplxmodule/nn/modules/__init__.py
cplxmodule/nn/modules/activation.py
cplxmodule/nn/modules/base.py
cplxmodule/nn/modules/batchnorm.py
cplxmodule/nn/modules/casting.py
cplxmodule/nn/modules/container.py
cplxmodule/nn/modules/conv.py
cplxmodule/nn/modules/extra.py
cplxmodule/nn/modules/linear.py
cplxmodule/nn/modules/pooling.py
cplxmodule/nn/relevance/__init__.py
cplxmodule/nn/relevance/base.py
cplxmodule/nn/relevance/complex/__init__.py
cplxmodule/nn/relevance/complex/ard.py
cplxmodule/nn/relevance/complex/base.py
cplxmodule/nn/relevance/complex/vd.py
cplxmodule/nn/relevance/extensions/__init__.py
cplxmodule/nn/relevance/extensions/complex.py
cplxmodule/nn/relevance/extensions/real/__init__.py
cplxmodule/nn/relevance/extensions/real/ell_zero.py
cplxmodule/nn/relevance/extensions/real/lasso.py
cplxmodule/nn/relevance/real/__init__.py
cplxmodule/nn/relevance/real/ard.py
cplxmodule/nn/relevance/real/base.py
cplxmodule/nn/relevance/real/vd.py
cplxmodule/nn/utils/__init__.py
cplxmodule/nn/utils/sparsity.py
cplxmodule/utils/__init__.py
cplxmodule/utils/spectrum.py
cplxmodule/utils/views.py
cplxmodule-2022.6.dist-info/LICENSE
cplxmodule-2022.6.dist-info/METADATA
cplxmodule-2022.6.dist-info/WHEEL
cplxmodule-2022.6.dist-info/top_level.txt
cplxmodule-2022.6.dist-info/RECORD
