Metadata-Version: 2.1
Name: cplxmodule
Version: 2022.6
Summary: Variational Dropout and Complex-valued Neural Networks in pytorch
Home-page: https://github.com/ivannz/cplxmodule
Author: Ivan Nazarov
Author-email: ivan.nazarov@skolkovotech.ru
License: MIT License
Keywords: pytorch,variational dropout,complex-valued networks,sparsification
Requires-Python: >=3.7
License-File: LICENSE
Requires-Dist: torch (>=1.8)
Requires-Dist: numpy
Requires-Dist: scipy
